{
  "generatedAt": "2026-06-12T17:45:35.514Z",
  "specimens": {
    "weeple": {
      "weeklyCommits": 100,
      "lastShipDays": 0
    },
    "muse-prompt-studio": {
      "weeklyCommits": 0,
      "lastShipDays": 27
    },
    "srt-saas": {
      "weeklyCommits": 0,
      "lastShipDays": 19
    },
    "tokodachi": {
      "weeklyCommits": 77,
      "lastShipDays": 0
    },
    "rightbefore": {
      "weeklyCommits": 1,
      "lastShipDays": 1
    },
    "kage-studio": {
      "weeklyCommits": 0,
      "lastShipDays": 4
    },
    "beep-get": {
      "weeklyCommits": 10,
      "lastShipDays": 3
    },
    "orido": {
      "weeklyCommits": 14,
      "lastShipDays": 5
    },
    "receipt-anything": {
      "weeklyCommits": 0,
      "lastShipDays": 2
    },
    "flatsnap": {
      "weeklyCommits": 0,
      "lastShipDays": 81
    },
    "diffwatch": {
      "weeklyCommits": 0,
      "lastShipDays": 68
    },
    "searchmachine": {
      "weeklyCommits": 0,
      "lastShipDays": 62
    },
    "youtube-shorts-music": {
      "weeklyCommits": 0,
      "lastShipDays": 59
    },
    "ai-threads": {
      "weeklyCommits": 2,
      "lastShipDays": 0
    }
  }
}
